programaA.py
pacote0770-0.0.1.dist-info/LICENSE
pacote0770-0.0.1.dist-info/METADATA
pacote0770-0.0.1.dist-info/WHEEL
pacote0770-0.0.1.dist-info/top_level.txt
pacote0770-0.0.1.dist-info/RECORD
