Metadata-Version: 2.1
Name: pacote0770
Version: 0.0.1
Summary: Pacote Teste
Author: Jefferson Figueiredo Dantas
Author-email: jeffersonfdantas95@gmail.com
License: MIT License
Keywords: Pacote
License-File: LICENSE
Requires-Dist: numpy
